pygoreadability-0.2.7.dist-info/RECORD
pygoreadability-0.2.7.dist-info/WHEEL
pygoreadability-0.2.7.dist-info/top_level.txt
pygoreadability-0.2.7.dist-info/METADATA
pygoreadability-0.2.7.dist-info/licenses/LICENSE
pygoreadability/libgoreadability.h
pygoreadability/__init__.py
pygoreadability/libgoreadability.dylib
pygoreadability/_binding.py
