Metadata-Version: 2.4
Name: pygoreadability
Version: 0.2.7
Summary: CPython bindings for go-readability (FromString)
Author: Kim Seonghyeon
License: MIT
Classifier: Programming Language :: Python :: 3
Classifier: Programming Language :: Python :: 3 :: Only
Classifier: Programming Language :: C
Classifier: Programming Language :: Go
Classifier: Operating System :: MacOS :: MacOS X
Classifier: Operating System :: POSIX :: Linux
Requires-Python: >=3.9
License-File: LICENSE
Dynamic: license-file
